[{"stop_id":"U1146Z98","name":"Hlavní nádraží","arrival_time":"22:36:00","departure_time":"22:36:00","is_passed":false},{"stop_id":"U15425Z11","name":"Šakvice, železniční stanice","arrival_time":"22:54:00","departure_time":"22:55:00","is_passed":false},{"stop_id":"U15537Z11","name":"Zaječí, železniční stanice","arrival_time":"22:59:00","departure_time":"23:00:00","is_passed":false},{"stop_id":"U25501Z11","name":"Rakvice","arrival_time":"23:03:00","departure_time":"23:03:00","is_passed":false},{"stop_id":"U15619Z11","name":"Podivín, železniční stanice","arrival_time":"23:07:00","departure_time":"23:08:00","is_passed":false},{"stop_id":"U15729Z11","name":"Břeclav, autobusové nádraží","arrival_time":"23:14:00","departure_time":"23:21:00","is_passed":false},{"stop_id":"U19129Z11","name":"Moravská Nová Ves, železniční stanice","arrival_time":"23:28:00","departure_time":"23:29:00","is_passed":false},{"stop_id":"U19001Z21","name":"Hodonín, autobusové nádraží","arrival_time":"23:36:00","departure_time":"23:36:00","is_passed":false}]