[{"stop_id":"U12633Z1","name":"Boskovice, 17. listopadu","arrival_time":"7:11:00","departure_time":"7:11:00","lat":49.488891,"lon":16.661476,"is_passed":false},{"stop_id":"U12635Z10","name":"Boskovice, aut.st.","arrival_time":"7:16:00","departure_time":"7:16:00","lat":49.49169,"lon":16.653337,"is_passed":false},{"stop_id":"U12650Z2","name":"Boskovice, nemocnice","arrival_time":"7:18:00","departure_time":"7:18:00","lat":49.49167,"lon":16.644917,"is_passed":false},{"stop_id":"U12648Z2","name":"Boskovice, Mladkov","arrival_time":"7:21:00","departure_time":"7:21:00","lat":49.490705,"lon":16.61905,"is_passed":false},{"stop_id":"U12676Z5","name":"Skalice nad Svitavou, žel.st.","arrival_time":"7:24:00","departure_time":"7:30:00","lat":49.480279,"lon":16.608801,"is_passed":false},{"stop_id":"U12663Z2","name":"Jabloňany, rozc.","arrival_time":"7:33:00","departure_time":"7:33:00","lat":49.47452,"lon":16.59455,"is_passed":false},{"stop_id":"U12665Z2","name":"Krhov","arrival_time":"7:36:00","departure_time":"7:36:00","lat":49.463333,"lon":16.58325,"is_passed":false},{"stop_id":"U12686Z2","name":"Voděrady, nám.","arrival_time":"7:42:00","departure_time":"7:42:00","lat":49.481015,"lon":16.5602,"is_passed":false},{"stop_id":"U12666Z2","name":"Krhov, Pohodlí","arrival_time":"7:46:00","departure_time":"7:46:00","lat":49.462515,"lon":16.575063,"is_passed":false},{"stop_id":"U12529Z2","name":"Lysice, výzkum","arrival_time":"7:49:00","departure_time":"7:49:00","lat":49.456417,"lon":16.556818,"is_passed":false},{"stop_id":"U12524Z4","name":"Lysice, pohostinství","arrival_time":"7:51:00","departure_time":"8:04:00","lat":49.452446,"lon":16.537857,"is_passed":false},{"stop_id":"U12528Z2","name":"Lysice, Štěchovská","arrival_time":"8:06:00","departure_time":"8:06:00","lat":49.450907,"lon":16.527685,"is_passed":false},{"stop_id":"U12531Z2","name":"Štěchov","arrival_time":"8:09:00","departure_time":"8:09:00","lat":49.451917,"lon":16.506837,"is_passed":false},{"stop_id":"U12537Z2","name":"Kunčina Ves","arrival_time":"8:13:00","departure_time":"8:13:00","lat":49.447552,"lon":16.476215,"is_passed":false},{"stop_id":"U12457Z1","name":"Rašov, rozc. 1.0","arrival_time":"8:14:00","departure_time":"8:14:00","lat":49.438973,"lon":16.467463,"is_passed":false},{"stop_id":"U12536Z1","name":"Kozárov","arrival_time":"8:16:00","departure_time":"9:42:00","lat":49.443447,"lon":16.458255,"is_passed":false}]