[{"stop_id":"U12849Z1","name":"Úsobrno, závod","arrival_time":"17:15:00","departure_time":"17:15:00","is_passed":false},{"stop_id":"U12848Z2","name":"Úsobrno, hostinec","arrival_time":"17:17:00","departure_time":"17:17:00","is_passed":false},{"stop_id":"U12851Z1","name":"Úsobrno, pila","arrival_time":"17:18:00","departure_time":"17:18:00","is_passed":false},{"stop_id":"U12822Z2","name":"Uhřice","arrival_time":"17:23:00","departure_time":"17:23:00","is_passed":false},{"stop_id":"U12823Z1","name":"Uhřice, točna","arrival_time":"17:24:00","departure_time":"17:24:00","is_passed":false},{"stop_id":"U12811Z13","name":"Cetkovice, MŠ","arrival_time":"17:27:00","departure_time":"17:27:00","is_passed":false},{"stop_id":"U12810Z13","name":"Cetkovice","arrival_time":"17:28:00","departure_time":"17:28:00","is_passed":false}]