[{"stop_id":"U18026Z81","name":"Znojmo, Popice, u kostela","arrival_time":"18:45:00","departure_time":"18:45:00","is_passed":false},{"stop_id":"U18070Z82","name":"Znojmo, Konice, rozcestí","arrival_time":"18:47:00","departure_time":"18:47:00","is_passed":false},{"stop_id":"U18184Z81","name":"Nový Šaldorf-Sedlešovice, Modré sklepy","arrival_time":"18:49:00","departure_time":"18:49:00","is_passed":false},{"stop_id":"U18102Z82","name":"Nový Šaldorf-Sedlešovice, u bytovky","arrival_time":"18:52:00","departure_time":"18:52:00","is_passed":false},{"stop_id":"U18103Z82","name":"Nový Šaldorf-Sedlešovice, Sedlešovice","arrival_time":"18:53:00","departure_time":"18:53:00","is_passed":false},{"stop_id":"U18024Z82","name":"Znojmo, Melkusova, plavecký bazén","arrival_time":"18:55:00","departure_time":"18:55:00","is_passed":false},{"stop_id":"U18023Z82","name":"Znojmo, Dukelská, sídliště","arrival_time":"18:57:00","departure_time":"18:57:00","is_passed":false},{"stop_id":"U18022Z82","name":"Znojmo, Vídeňská, u školy","arrival_time":"18:58:00","departure_time":"18:58:00","is_passed":false},{"stop_id":"U18021Z82","name":"Znojmo, Vídeňská, Pražákova","arrival_time":"19:00:00","departure_time":"19:00:00","is_passed":false},{"stop_id":"U18008Z82","name":"Znojmo, Vídeňská, Na Rejdišti","arrival_time":"19:01:00","departure_time":"19:01:00","is_passed":false},{"stop_id":"U18009Z84","name":"Znojmo, autobusové nádraží","arrival_time":"19:04:00","departure_time":"23:08:00","is_passed":false}]