[{"stop_id":"U15424Z2","name":"Šakvice, obecní úřad","arrival_time":"14:06:00","departure_time":"14:06:00","lat":48.896868,"lon":16.717445,"is_passed":false},{"stop_id":"U15423Z2","name":"Šakvice, horní konec","arrival_time":"14:08:00","departure_time":"14:08:00","lat":48.899162,"lon":16.712955,"is_passed":false},{"stop_id":"U15408Z1","name":"Hustopeče, plnírna","arrival_time":"14:13:00","departure_time":"14:13:00","lat":48.917168,"lon":16.703175,"is_passed":false},{"stop_id":"U15413Z1","name":"Popice, rozcestí","arrival_time":"14:15:00","departure_time":"14:15:00","lat":48.919667,"lon":16.68427,"is_passed":false},{"stop_id":"U15412Z1","name":"Popice","arrival_time":"14:16:00","departure_time":"14:16:00","lat":48.928484,"lon":16.664852,"is_passed":false}]