[{"stop_id":"U12801Z1","name":"Kunice","arrival_time":"7:18:00","departure_time":"7:18:00","is_passed":false},{"stop_id":"U12802Z1","name":"Lhota u Lysic","arrival_time":"7:22:00","departure_time":"7:22:00","is_passed":false},{"stop_id":"U12806Z1","name":"Lysice, Záoboří","arrival_time":"7:25:00","departure_time":"7:25:00","is_passed":false},{"stop_id":"U12519Z2","name":"Drnovice","arrival_time":"7:31:00","departure_time":"7:31:00","is_passed":false},{"stop_id":"U12520Z2","name":"Drnovice, hor.zast.","arrival_time":"7:33:00","departure_time":"7:33:00","is_passed":false},{"stop_id":"U12805Z1","name":"Lysice, škola točna","arrival_time":"7:36:00","departure_time":"7:36:00","is_passed":false},{"stop_id":"U12524Z51","name":"Lysice, pohostinství","arrival_time":"7:39:00","departure_time":"10:12:00","is_passed":false}]