[{"stop_id":"U14242Z2","name":"Zastávka, železniční stanice","arrival_time":"6:47:00","departure_time":"6:47:00","is_passed":false},{"stop_id":"U14239Z2","name":"Zastávka, Dům zdraví","arrival_time":"6:48:00","departure_time":"6:48:00","is_passed":false},{"stop_id":"U14225Z2","name":"Rosice, ADOSA","arrival_time":"6:50:00","departure_time":"6:50:00","is_passed":false},{"stop_id":"U14229Z2","name":"Rosice, Kamínky","arrival_time":"6:52:00","departure_time":"6:52:00","is_passed":false},{"stop_id":"U14235Z2","name":"Rosice, Trávníky","arrival_time":"6:54:00","departure_time":"6:54:00","is_passed":false},{"stop_id":"U14226Z2","name":"Rosice, Brněnská","arrival_time":"6:56:00","departure_time":"6:56:00","is_passed":false},{"stop_id":"U14233Z2","name":"Rosice, STK","arrival_time":"6:57:00","departure_time":"6:57:00","is_passed":false},{"stop_id":"U14111Z2","name":"Omice, Kývalka","arrival_time":"7:01:00","departure_time":"7:01:00","is_passed":false},{"stop_id":"U14133Z2","name":"Popůvky, Vintrovna","arrival_time":"7:04:00","departure_time":"7:04:00","is_passed":false},{"stop_id":"U14160Z2","name":"Troubsko, Veselka","arrival_time":"7:06:00","departure_time":"7:06:00","is_passed":false},{"stop_id":"U14107Z2","name":"Troubsko, Kovopodnik","arrival_time":"7:07:00","departure_time":"7:07:00","is_passed":false},{"stop_id":"U1672Z2","name":"Tranzitní plynovod","arrival_time":"7:08:00","departure_time":"7:08:00","is_passed":false},{"stop_id":"U1516Z1","name":"Pražská","arrival_time":"7:09:00","departure_time":"7:09:00","is_passed":false},{"stop_id":"U1568Z2","name":"Skalní","arrival_time":"7:10:00","departure_time":"7:10:00","is_passed":false},{"stop_id":"U1202Z2","name":"Jemelkova","arrival_time":"7:11:00","departure_time":"7:11:00","is_passed":false},{"stop_id":"U1632Z2","name":"Svážná","arrival_time":"7:12:00","departure_time":"7:12:00","is_passed":false},{"stop_id":"U1429Z7","name":"Nemocnice Bohunice","arrival_time":"7:15:00","departure_time":"7:42:00","is_passed":false}]