[{"stop_id":"U12342Z88","name":"Blansko, aut. st.","arrival_time":"7:17:00","departure_time":"7:17:00","lat":49.353413,"lon":16.647217,"is_passed":false},{"stop_id":"U12391Z81","name":"Blansko, Seifertova","arrival_time":"7:19:00","departure_time":"7:19:00","lat":49.362427,"lon":16.645358,"is_passed":false},{"stop_id":"U12373Z81","name":"Blansko, Bezručova","arrival_time":"7:21:00","departure_time":"7:21:00","lat":49.370599,"lon":16.645997,"is_passed":false},{"stop_id":"U12399Z82","name":"Blansko, Zborovce","arrival_time":"7:22:00","departure_time":"7:22:00","lat":49.37277,"lon":16.65012,"is_passed":false}]