[{"stop_id":"U13459Z2","name":"Svatoslav, obecní úřad","arrival_time":"6:50:00","departure_time":"6:50:00","is_passed":false},{"stop_id":"U13458Z2","name":"Svatoslav, horní konec","arrival_time":"6:51:00","departure_time":"6:51:00","is_passed":false},{"stop_id":"U14413Z2","name":"Velká Bíteš, Pánov, rozcestí","arrival_time":"6:54:00","departure_time":"6:54:00","is_passed":false},{"stop_id":"U14417Z1","name":"Křoví, I","arrival_time":"6:57:00","departure_time":"6:57:00","is_passed":false},{"stop_id":"U14418Z51","name":"Křoví, II","arrival_time":"6:59:00","departure_time":"7:02:00","is_passed":false}]