{"769":[{"stop_id":"U18009Z21","name":"Znojmo, autobusové nádraží","arrival_time":"15:59:00","departure_time":"15:59:00","lat":48.852761,"lon":16.059287,"is_passed":false},{"stop_id":"U28102Z11","name":"Dyje","arrival_time":"16:04:00","departure_time":"16:04:00","lat":48.850047,"lon":16.1205,"is_passed":false},{"stop_id":"U28101Z11","name":"Hodonice","arrival_time":"16:08:00","departure_time":"16:09:00","lat":48.841514,"lon":16.164403,"is_passed":false},{"stop_id":"U18208Z11","name":"Božice, železniční stanice","arrival_time":"16:18:00","departure_time":"16:18:00","lat":48.823282,"lon":16.287832,"is_passed":false},{"stop_id":"U15637Z11","name":"Hrušovany nad Jevišovkou, žel. st.","arrival_time":"16:25:00","departure_time":"16:28:00","lat":48.810029,"lon":16.383137,"is_passed":false},{"stop_id":"U25505Z11","name":"Jevišovka","arrival_time":"16:34:00","departure_time":"16:34:00","lat":48.820272,"lon":16.467125,"is_passed":false},{"stop_id":"U15563Z11","name":"Novosedly, železniční stanice","arrival_time":"16:37:00","departure_time":"16:37:00","lat":48.825719,"lon":16.49405,"is_passed":false},{"stop_id":"U25602Z11","name":"Dobré Pole","arrival_time":"16:41:00","departure_time":"16:41:00","lat":48.820008,"lon":16.533833,"is_passed":false},{"stop_id":"U25601Z11","name":"Březí","arrival_time":"16:44:00","departure_time":"16:44:00","lat":48.812925,"lon":16.554169,"is_passed":false},{"stop_id":"U15714Z11","name":"Mikulov, železniční stanice","arrival_time":"16:49:00","departure_time":"16:51:00","lat":48.802203,"lon":16.625492,"is_passed":false},{"stop_id":"U25701Z11","name":"Sedlec u Mikulova","arrival_time":"16:56:00","departure_time":"16:58:00","lat":48.774727,"lon":16.697093,"is_passed":false},{"stop_id":"U15828Z11","name":"Valtice, železniční zastávka","arrival_time":"17:04:00","departure_time":"17:04:00","lat":48.748776,"lon":16.762369,"is_passed":false},{"stop_id":"U15729Z15","name":"Břeclav, autobusové nádraží","arrival_time":"17:13:00","departure_time":"17:41:00","lat":48.753851,"lon":16.893169,"is_passed":false}],"7690":[{"stop_id":"U16509Z4","name":"Nesovice, železniční stanice","arrival_time":"10:22:00","departure_time":"10:22:00","lat":49.149095,"lon":17.079312,"is_passed":false},{"stop_id":"U16506Z1","name":"Nesovice, obecní úřad","arrival_time":"10:23:00","departure_time":"10:23:00","lat":49.148808,"lon":17.082913,"is_passed":false},{"stop_id":"U16505Z1","name":"Nesovice, Kotáry","arrival_time":"10:24:00","departure_time":"10:24:00","lat":49.149117,"lon":17.092515,"is_passed":false},{"stop_id":"U16512Z1","name":"Snovídky","arrival_time":"10:28:00","departure_time":"10:28:00","lat":49.13304,"lon":17.10617,"is_passed":false},{"stop_id":"U16503Z1","name":"Nemotice, železniční stanice","arrival_time":"10:31:00","departure_time":"10:31:00","lat":49.13415,"lon":17.116908,"is_passed":false},{"stop_id":"U16504Z1","name":"Nemotice","arrival_time":"10:32:00","departure_time":"10:32:00","lat":49.12968,"lon":17.124725,"is_passed":false},{"stop_id":"U16623Z1","name":"Mouchnice, Na Požárech","arrival_time":"10:37:00","departure_time":"10:37:00","lat":49.116308,"lon":17.135068,"is_passed":false},{"stop_id":"U16624Z1","name":"Mouchnice","arrival_time":"10:38:00","departure_time":"10:38:00","lat":49.112052,"lon":17.135112,"is_passed":false},{"stop_id":"U16793Z2","name":"Koryčany, náměstí","arrival_time":"10:41:00","departure_time":"12:00:00","lat":49.106225,"lon":17.163642,"is_passed":false}],"7691":[{"stop_id":"U16793Z1","name":"Koryčany, náměstí","arrival_time":"12:00:00","departure_time":"12:00:00","lat":49.106098,"lon":17.163237,"is_passed":false},{"stop_id":"U16624Z2","name":"Mouchnice","arrival_time":"12:03:00","departure_time":"12:03:00","lat":49.112142,"lon":17.135145,"is_passed":false},{"stop_id":"U16623Z2","name":"Mouchnice, Na Požárech","arrival_time":"12:04:00","departure_time":"12:04:00","lat":49.116365,"lon":17.135258,"is_passed":false},{"stop_id":"U16504Z2","name":"Nemotice","arrival_time":"12:09:00","departure_time":"12:09:00","lat":49.129713,"lon":17.125008,"is_passed":false},{"stop_id":"U16503Z2","name":"Nemotice, železniční stanice","arrival_time":"12:10:00","departure_time":"12:10:00","lat":49.134107,"lon":17.116798,"is_passed":false},{"stop_id":"U16512Z2","name":"Snovídky","arrival_time":"12:13:00","departure_time":"12:13:00","lat":49.133113,"lon":17.106213,"is_passed":false},{"stop_id":"U16505Z2","name":"Nesovice, Kotáry","arrival_time":"12:17:00","departure_time":"12:17:00","lat":49.149153,"lon":17.092268,"is_passed":false},{"stop_id":"U16506Z2","name":"Nesovice, obecní úřad","arrival_time":"12:18:00","departure_time":"12:18:00","lat":49.148482,"lon":17.082872,"is_passed":false},{"stop_id":"U16509Z5","name":"Nesovice, železniční stanice","arrival_time":"12:19:00","departure_time":"12:19:00","lat":49.149095,"lon":17.079312,"is_passed":false}],"7692":[{"stop_id":"U16509Z2","name":"Nesovice, železniční stanice","arrival_time":"12:20:00","departure_time":"12:20:00","lat":49.149095,"lon":17.079312,"is_passed":false},{"stop_id":"U16557Z2","name":"Nesovice, čerpací stanice","arrival_time":"12:21:00","departure_time":"12:21:00","lat":49.149638,"lon":17.080161,"is_passed":false},{"stop_id":"U16511Z2","name":"Nevojice, točna","arrival_time":"12:26:00","departure_time":"12:26:00","lat":49.137013,"lon":17.047757,"is_passed":false},{"stop_id":"U16434Z2","name":"Bučovice, Vícemilice","arrival_time":"12:29:00","departure_time":"12:29:00","lat":49.14097,"lon":17.018388,"is_passed":false},{"stop_id":"U16451Z1","name":"Bučovice, zdravotní středisko","arrival_time":"12:31:00","departure_time":"12:31:00","lat":49.14811,"lon":17.005643,"is_passed":false},{"stop_id":"U16463Z3","name":"Bučovice, železniční stanice","arrival_time":"12:33:00","departure_time":"12:33:00","lat":49.145968,"lon":17.000305,"is_passed":false},{"stop_id":"U16401Z6","name":"Bučovice, aut. st.","arrival_time":"12:34:00","departure_time":"12:34:00","lat":49.148057,"lon":17.001665,"is_passed":false},{"stop_id":"U16435Z2","name":"Bučovice, dům mládeže","arrival_time":"12:36:00","departure_time":"12:36:00","lat":49.15278,"lon":17.009682,"is_passed":false},{"stop_id":"U16407Z1","name":"Bučovice, u školy","arrival_time":"12:39:00","departure_time":"12:39:00","lat":49.155433,"lon":17.000171,"is_passed":false}],"7693":[{"stop_id":"U16407Z1","name":"Bučovice, u školy","arrival_time":"12:42:00","departure_time":"12:42:00","lat":49.155433,"lon":17.000171,"is_passed":false},{"stop_id":"U16401Z3","name":"Bučovice, aut. st.","arrival_time":"12:47:00","departure_time":"12:47:00","lat":49.148057,"lon":17.001665,"is_passed":false},{"stop_id":"U16432Z1","name":"Bučovice, Kloboučky, škola","arrival_time":"12:51:00","departure_time":"12:51:00","lat":49.133683,"lon":17.006302,"is_passed":false},{"stop_id":"U16433Z1","name":"Bučovice, Kloboučky, točna","arrival_time":"12:54:00","departure_time":"12:58:00","lat":49.131123,"lon":17.01126,"is_passed":false}],"7694":[{"stop_id":"U16433Z2","name":"Bučovice, Kloboučky, točna","arrival_time":"12:58:00","departure_time":"12:58:00","lat":49.131123,"lon":17.01126,"is_passed":false},{"stop_id":"U16432Z2","name":"Bučovice, Kloboučky, škola","arrival_time":"13:01:00","departure_time":"13:01:00","lat":49.133775,"lon":17.006257,"is_passed":false},{"stop_id":"U16401Z20","name":"Bučovice, aut. st.","arrival_time":"13:04:00","departure_time":"13:05:00","lat":49.148057,"lon":17.001665,"is_passed":false}],"7695":[{"stop_id":"U16407Z1","name":"Bučovice, u školy","arrival_time":"13:25:00","departure_time":"13:25:00","lat":49.155433,"lon":17.000171,"is_passed":false},{"stop_id":"U16435Z1","name":"Bučovice, dům mládeže","arrival_time":"13:28:00","departure_time":"13:28:00","lat":49.1528,"lon":17.009197,"is_passed":false},{"stop_id":"U16401Z6","name":"Bučovice, aut. st.","arrival_time":"13:30:00","departure_time":"13:30:00","lat":49.148057,"lon":17.001665,"is_passed":false},{"stop_id":"U16451Z2","name":"Bučovice, zdravotní středisko","arrival_time":"13:32:00","departure_time":"13:32:00","lat":49.14811,"lon":17.005643,"is_passed":false},{"stop_id":"U16434Z1","name":"Bučovice, Vícemilice","arrival_time":"13:34:00","departure_time":"13:34:00","lat":49.14097,"lon":17.018388,"is_passed":false},{"stop_id":"U16511Z1","name":"Nevojice, točna","arrival_time":"13:38:00","departure_time":"13:38:00","lat":49.137013,"lon":17.047757,"is_passed":false},{"stop_id":"U16557Z1","name":"Nesovice, čerpací stanice","arrival_time":"13:43:00","departure_time":"13:43:00","lat":49.149513,"lon":17.080224,"is_passed":false},{"stop_id":"U16509Z1","name":"Nesovice, železniční stanice","arrival_time":"13:44:00","departure_time":"13:44:00","lat":49.149095,"lon":17.079312,"is_passed":false}],"7696":[{"stop_id":"U16509Z3","name":"Nesovice, železniční stanice","arrival_time":"13:44:00","departure_time":"13:44:00","lat":49.149095,"lon":17.079312,"is_passed":false},{"stop_id":"U16630Z1","name":"Dobročkovice, rozcestí","arrival_time":"13:49:00","departure_time":"13:49:00","lat":49.149935,"lon":17.121458,"is_passed":false},{"stop_id":"U16627Z1","name":"Brankovice, škola","arrival_time":"13:54:00","departure_time":"14:03:00","lat":49.15603,"lon":17.129673,"is_passed":false}],"7697":[{"stop_id":"U16627Z1","name":"Brankovice, škola","arrival_time":"14:03:00","departure_time":"14:03:00","lat":49.15603,"lon":17.129673,"is_passed":false},{"stop_id":"U16630Z2","name":"Dobročkovice, rozcestí","arrival_time":"14:08:00","departure_time":"14:08:00","lat":49.150134,"lon":17.121907,"is_passed":false},{"stop_id":"U16631Z1","name":"Dobročkovice","arrival_time":"14:11:00","departure_time":"14:11:00","lat":49.16243,"lon":17.10881,"is_passed":false},{"stop_id":"U16509Z3","name":"Nesovice, železniční stanice","arrival_time":"14:17:00","departure_time":"14:17:00","lat":49.149095,"lon":17.079312,"is_passed":false}],"7698":[{"stop_id":"U16509Z4","name":"Nesovice, železniční stanice","arrival_time":"14:22:00","departure_time":"14:22:00","lat":49.149095,"lon":17.079312,"is_passed":false},{"stop_id":"U16506Z1","name":"Nesovice, obecní úřad","arrival_time":"14:23:00","departure_time":"14:23:00","lat":49.148808,"lon":17.082913,"is_passed":false},{"stop_id":"U16505Z1","name":"Nesovice, Kotáry","arrival_time":"14:24:00","departure_time":"14:24:00","lat":49.149117,"lon":17.092515,"is_passed":false},{"stop_id":"U16512Z1","name":"Snovídky","arrival_time":"14:28:00","departure_time":"14:28:00","lat":49.13304,"lon":17.10617,"is_passed":false},{"stop_id":"U16503Z1","name":"Nemotice, železniční stanice","arrival_time":"14:31:00","departure_time":"14:31:00","lat":49.13415,"lon":17.116908,"is_passed":false},{"stop_id":"U16504Z1","name":"Nemotice","arrival_time":"14:32:00","departure_time":"14:32:00","lat":49.12968,"lon":17.124725,"is_passed":false}],"7699":[{"stop_id":"U16504Z2","name":"Nemotice","arrival_time":"14:32:00","departure_time":"14:32:00","lat":49.129713,"lon":17.125008,"is_passed":false},{"stop_id":"U16503Z2","name":"Nemotice, železniční stanice","arrival_time":"14:33:00","departure_time":"14:33:00","lat":49.134107,"lon":17.116798,"is_passed":false},{"stop_id":"U16512Z2","name":"Snovídky","arrival_time":"14:36:00","departure_time":"14:36:00","lat":49.133113,"lon":17.106213,"is_passed":false},{"stop_id":"U16505Z2","name":"Nesovice, Kotáry","arrival_time":"14:40:00","departure_time":"14:40:00","lat":49.149153,"lon":17.092268,"is_passed":false},{"stop_id":"U16506Z2","name":"Nesovice, obecní úřad","arrival_time":"14:41:00","departure_time":"14:41:00","lat":49.148482,"lon":17.082872,"is_passed":false},{"stop_id":"U16509Z5","name":"Nesovice, železniční stanice","arrival_time":"14:42:00","departure_time":"14:42:00","lat":49.149095,"lon":17.079312,"is_passed":false}]}