[{"stop_id":"U16608Z15","name":"Kyjov, aut. st.","arrival_time":"10:10:00","departure_time":"10:10:00","is_passed":false},{"stop_id":"U16639Z1","name":"Kyjov, nemocnice, křižovatka","arrival_time":"10:12:00","departure_time":"10:12:00","is_passed":false},{"stop_id":"U16811Z1","name":"Svatobořice-Mistřín, textilka","arrival_time":"10:16:00","departure_time":"10:16:00","is_passed":false},{"stop_id":"U16809Z1","name":"Svatobořice-Mistřín, restaurace","arrival_time":"10:18:00","departure_time":"10:18:00","is_passed":false},{"stop_id":"U16806Z1","name":"Svatobořice-Mistřín, kulturní dům","arrival_time":"10:20:00","departure_time":"10:20:00","is_passed":false},{"stop_id":"U16810Z1","name":"Svatobořice-Mistřín, škola","arrival_time":"10:21:00","departure_time":"10:21:00","is_passed":false},{"stop_id":"U16807Z3","name":"Svatobořice-Mistřín, Mistřín","arrival_time":"10:23:00","departure_time":"10:23:00","is_passed":false},{"stop_id":"U16808Z1","name":"Svatobořice-Mistřín, mlýn","arrival_time":"10:24:00","departure_time":"10:24:00","is_passed":false},{"stop_id":"U16803Z1","name":"Milotice, rozcestí","arrival_time":"10:26:00","departure_time":"10:26:00","is_passed":false},{"stop_id":"U19140Z1","name":"Dubňany, kemp Josef","arrival_time":"10:28:00","departure_time":"10:28:00","is_passed":false},{"stop_id":"U19146Z2","name":"Dubňany, obchodní dům","arrival_time":"10:31:00","departure_time":"10:31:00","is_passed":false},{"stop_id":"U19151Z2","name":"Dubňany, u mlýna","arrival_time":"10:33:00","departure_time":"10:33:00","is_passed":false},{"stop_id":"U19149Z1","name":"Dubňany, škola","arrival_time":"10:34:00","departure_time":"10:34:00","is_passed":false},{"stop_id":"U19012Z1","name":"Hodonín, STS","arrival_time":"10:38:00","departure_time":"10:38:00","is_passed":false},{"stop_id":"U19002Z1","name":"Hodonín, Brněnská","arrival_time":"10:40:00","departure_time":"10:40:00","is_passed":false},{"stop_id":"U19001Z50","name":"Hodonín, autobusové nádraží","arrival_time":"10:43:00","departure_time":"10:47:00","is_passed":false}]