[{"stop_id":"U17423Z7","name":"Vyškov, Autobusové nádraží","arrival_time":"9:16:00","departure_time":"9:16:00","is_passed":false},{"stop_id":"U17429Z2","name":"Vyškov, garáže ČSAD","arrival_time":"9:18:00","departure_time":"9:18:00","is_passed":false},{"stop_id":"U17435Z2","name":"Vyškov, Nouzka","arrival_time":"9:19:00","departure_time":"9:19:00","is_passed":false},{"stop_id":"U17428Z2","name":"Vyškov, Drnovská Bioveta","arrival_time":"9:22:00","departure_time":"9:22:00","is_passed":false},{"stop_id":"U17328Z2","name":"Luleč, rozcestí","arrival_time":"9:24:00","departure_time":"9:24:00","is_passed":false},{"stop_id":"U17344Z2","name":"Tučapy, rozcestí","arrival_time":"9:26:00","departure_time":"9:26:00","is_passed":false},{"stop_id":"U17311Z4","name":"Komořany, EDP","arrival_time":"9:28:00","departure_time":"9:28:00","is_passed":false},{"stop_id":"U17331Z2","name":"Rousínov, Čechyně, rozcestí","arrival_time":"9:31:00","departure_time":"9:31:00","is_passed":false},{"stop_id":"U17335Z3","name":"Rousínov, autobusová stanice","arrival_time":"9:33:00","departure_time":"9:35:00","is_passed":false},{"stop_id":"U1677Z2","name":"Tržní","arrival_time":"9:54:00","departure_time":"9:54:00","is_passed":false},{"stop_id":"U1696Z5","name":"ÚAN Zvonařka","arrival_time":"9:58:00","departure_time":"11:04:00","is_passed":false}]